pitop/common/__init__.py
pitop/common/bitwise_ops.py
pitop/common/command_runner.py
pitop/common/common_ids.py
pitop/common/common_names.py
pitop/common/configuration_file.py
pitop/common/counter.py
pitop/common/current_session_info.py
pitop/common/file_ops.py
pitop/common/firmware_device.py
pitop/common/flask_sockets.py
pitop/common/formatting.py
pitop/common/i2c_device.py
pitop/common/lock.py
pitop/common/logger.py
pitop/common/notifications.py
pitop/common/pt_os.py
pitop/common/ptdm.py
pitop/common/singleton.py
pitop/common/smbus_device.py
pitop/common/switch_user.py
pitop/common/sys_info.py
pitop/common/type_helper.py
pitop.common-0.34.3.post1.dist-info/METADATA
pitop.common-0.34.3.post1.dist-info/WHEEL
pitop.common-0.34.3.post1.dist-info/top_level.txt
pitop.common-0.34.3.post1.dist-info/RECORD
